{
  "type": "FeatureCollection",
  "name": "flower_survey",
  "crs": {
    "type": "name",
    "properties": {
      "name": "urn:ogc:def:crs:OGC:1.3:CRS84"
    }
  },
  "xy_coordinate_resolution": 1e-06,
  "features": [
    {
      "type": "Feature",
      "properties": {
        "site_id": "{3ca2d12d-9e1f-4c39-a2ca-5b0fe34ff5c8}",
        "name": "コマクサ",
        "status": "つぼみ",
        "radius_m": 15.0,
        "date": "2026-03-20",
        "photo": "https://drive.google.com/thumbnail?id=1zbBU4fm-PP6spoZUYd9jEJgUdyoEZQ9e&sz=w800",
        "memo": "コマクサa"
      },
      "geometry": {
        "type": "Point",
        "coordinates": [
          139.158552,
          35.857451
        ]
      }
    },
    {
      "type": "Feature",
      "properties": {
        "site_id": "{8c18a1be-2d16-4a4f-9ff9-1fd7af33f87e}",
        "name": "サクラ",
        "status": "見頃",
        "radius_m": 10.0,
        "date": "2026-03-20",
        "photo": "https://drive.google.com/thumbnail?id=1Wg-DaICAG9Bw6yVjfKfY7DcOTWBLmLIj&sz=w800",
        "memo": "サクラ1"
      },
      "geometry": {
        "type": "Point",
        "coordinates": [
          139.156666,
          35.858099
        ]
      }
    },
    {
      "type": "Feature",
      "properties": {
        "site_id": "{0aab9267-22cb-4ed8-a6a0-6aca2b30693f}",
        "name": "コマクサ",
        "status": "咲き始め",
        "radius_m": 8.0,
        "date": "2026-03-20",
        "photo": "https://drive.google.com/thumbnail?id=1OMgMkkRhKZErFjun3YOrUyNSOC-56SSx&sz=w800",
        "memo": "コマクサ1"
      },
      "geometry": {
        "type": "Point",
        "coordinates": [
          139.159866,
          35.856983
        ]
      }
    },
    {
      "type": "Feature",
      "properties": {
        "site_id": "{618b1c3e-611c-43e4-b7d2-685242c0cf01}",
        "name": "ふきのとう",
        "status": "つぼみ",
        "radius_m": 10.0,
        "date": "2026-03-18",
        "photo": "https://drive.google.com/thumbnail?id=1PPh1lKUAtxxOrqjBiiZkmMRssQaUeorL&sz=w800",
        "memo": null
      },
      "geometry": {
        "type": "Point",
        "coordinates": [
          139.155007,
          35.858756
        ]
      }
    }
  ]
}